{"cameraMode":{"drawMode":0,"name":"Shaded","section":"Shading Mode"},"sceneLighting":true,"audioPlay":false,"sceneViewState":{"showFog":true,"showMaterialUpdate":false,"showSkybox":true,"showFlares":true,"showImageEffects":true,"showParticleSystems":true},"in2DMode":false,"pivot":{"x":1.4807302951812745,"y":9.145051002502442,"z":-7.012016773223877},"rotation":{"x":-0.2481849491596222,"y":0.12305247038602829,"z":-0.03179566562175751,"w":-0.9603392481803894},"size":0.8103153109550476,"orthographic":false}